ydk_models_openconfig-0.1.6-nspkg.pth
ydk/models/openconfig/__init__.py
ydk/models/openconfig/_yang_ns.py
ydk/models/openconfig/openconfig_acl.py
ydk/models/openconfig/openconfig_aft_types.py
ydk/models/openconfig/openconfig_bgp.py
ydk/models/openconfig/openconfig_bgp_policy.py
ydk/models/openconfig/openconfig_bgp_types.py
ydk/models/openconfig/openconfig_channel_monitor.py
ydk/models/openconfig/openconfig_if_aggregate.py
ydk/models/openconfig/openconfig_if_ethernet.py
ydk/models/openconfig/openconfig_if_ip.py
ydk/models/openconfig/openconfig_interfaces.py
ydk/models/openconfig/openconfig_isis.py
ydk/models/openconfig/openconfig_isis_lsdb_types.py
ydk/models/openconfig/openconfig_isis_types.py
ydk/models/openconfig/openconfig_lacp.py
ydk/models/openconfig/openconfig_lldp.py
ydk/models/openconfig/openconfig_lldp_types.py
ydk/models/openconfig/openconfig_local_routing.py
ydk/models/openconfig/openconfig_mpls.py
ydk/models/openconfig/openconfig_mpls_types.py
ydk/models/openconfig/openconfig_network_instance.py
ydk/models/openconfig/openconfig_network_instance_types.py
ydk/models/openconfig/openconfig_optical_amplifier.py
ydk/models/openconfig/openconfig_packet_match_types.py
ydk/models/openconfig/openconfig_platform.py
ydk/models/openconfig/openconfig_platform_types.py
ydk/models/openconfig/openconfig_policy_types.py
ydk/models/openconfig/openconfig_rib_bgp.py
ydk/models/openconfig/openconfig_rib_bgp_types.py
ydk/models/openconfig/openconfig_routing_policy.py
ydk/models/openconfig/openconfig_segment_routing.py
ydk/models/openconfig/openconfig_telemetry.py
ydk/models/openconfig/openconfig_terminal_device.py
ydk/models/openconfig/openconfig_transport_line_common.py
ydk/models/openconfig/openconfig_transport_line_protection.py
ydk/models/openconfig/openconfig_transport_types.py
ydk/models/openconfig/openconfig_types.py
ydk/models/openconfig/openconfig_vlan.py
ydk/models/openconfig/openconfig_vlan_types.py
ydk_models_openconfig-0.1.6.dist-info/DESCRIPTION.rst
ydk_models_openconfig-0.1.6.dist-info/METADATA
ydk_models_openconfig-0.1.6.dist-info/RECORD
ydk_models_openconfig-0.1.6.dist-info/WHEEL
ydk_models_openconfig-0.1.6.dist-info/metadata.json
ydk_models_openconfig-0.1.6.dist-info/namespace_packages.txt
ydk_models_openconfig-0.1.6.dist-info/top_level.txt
